kahi_scienti_sources/Kahi_scienti_sources.py
kahi_scienti_sources/__init__.py
kahi_scienti_sources/_version.py
Kahi_scienti_sources-0.1.2b0.dist-info/LICENSE
Kahi_scienti_sources-0.1.2b0.dist-info/METADATA
Kahi_scienti_sources-0.1.2b0.dist-info/WHEEL
Kahi_scienti_sources-0.1.2b0.dist-info/top_level.txt
Kahi_scienti_sources-0.1.2b0.dist-info/RECORD
