Metadata-Version: 2.1
Name: Kahi_scienti_sources
Version: 0.1.2b0
Summary: Kahi plugin to insert or update sources from scienti
Home-page: https://github.com/colav/Kahi_plugins
Author: Colav
Author-email: colav@udea.edu.co
License: BSD
License-File: LICENSE
Requires-Dist: kahi
Requires-Dist: langid
Requires-Dist: pymongo
Requires-Dist: kahi-impactu-utils
